{"Animal Friendship": ["Salida (ToA) (Named)", "Yuan-ti Pureblood (MM)"], "Animate Dead": ["Kraul Death Priest (GGR)"], "Armor of Agathys": ["Sahuagin Warlock of Uk'otoa (EGW)"], "Arms of Hadar": ["Sahuagin Warlock of Uk'otoa (EGW)"], "Augury": ["Anchorite of Talos (DIP)", "Auspicia Dran (AI) (Named)", "Oracle (MOT)"], "Blade Ward": ["Duergar Soulblade (MTF)"], "Bless": ["Anchorite of Talos (DIP)", "Couatl (MM)", "Horncaller (GGR)", "Oracle (MOT)"], "Blight": ["Kraul Death Priest (GGR)"], "Blindness/Deafness": ["Deep Gnome (Svirfneblin) (MM)", "Jimjar (OotA) (Named)", "Mev Flintknapper (OotA) (Named)", "Peebles (OotA) (Named)", "Svirfneblin Wererat (OotA)", "The Pudding King (OotA) (Named)"], "Blur": ["Deep Gnome (Svirfneblin) (MM)", "Jimjar (OotA) (Named)", "Mev Flintknapper (OotA) (Named)", "Peebles (OotA) (Named)", "Svirfneblin Wererat (OotA)", "The Pudding King (OotA) (Named)", "Thought Spy (GGR)"], "Charm Person": ["Bol'bara (EGW) (Named)", "Inspired (ERLW)", "Reaper of Bhaal (BGDIA)", "Thought Spy (GGR)"], "Chill Touch": ["Kraul Death Priest (GGR)"], "Chromatic Orb": ["Spellix Romwod (IDRotF) (Named)", "Tarkanan Assassin (ERLW)"], "Clairvoyance": ["Precognitive Mage (GGR)"], "Command": ["Duergar Keeper of the Flame (OotA)", "Rosie Beestinger (AI) (Named)"], "Confusion": ["Nilbog (VGM)"], "Conjure Animals": ["Horncaller (GGR)"], "Conjure Fey": ["Booyahg Slave of the Archfey (VGM)", "Warlock of the Archfey (VGM)"], "Counterspell": ["Counterflux Blastseeker (GGR)", "Sahuagin Warlock of Uk'otoa (EGW)"], "Create Food and Water": ["Couatl (MM)"], "Create or Destroy Water": ["Shoalar Quanderil (PotA) (Named)"], "Crown of Madness": ["Sahuagin Warlock of Uk'otoa (EGW)", "Spellix Romwod (IDRotF) (Named)"], "Cure Wounds": ["Couatl (MM)", "Quaggoth Thonot (MM)"], "Dancing Lights": ["Asha Vandree (OotA) (Named)", "Deep Roth\u00e9 (VGM)", "Deep Roth\u00e9 (VGM)", "Drow (MM)", "Drow Acolyte (OotA)", "Drow Bandit (OotA)", "Drow Cultist (OotA)", "Drow Guard (OotA)", "Drow Gunslinger (WDH)", "Drow Noble (OotA)", "Drow Scout (OotA)", "Drow Spy (OotA)", "Fel'rekt Lafeen (WDH) (Named)", "Hanne Hallen (OotA) (Named)", "Ishel (EGW) (Named)", "Junior Drow Priestess of Lolth (WDMM)", "K'thriss Drow'b (AI) (Named)", "Khalessa Draga (OotA) (Named)", "Krebbyg Masq'il'yr (WDH) (Named)", "Nezznar the Black Spider (LMoP) (Named)", "Sarith Kzekarit (OotA) (Named)", "Soluun Xibrindas (WDH) (Named)"], "Darkness": ["Asha Vandree (OotA) (Named)", "Captain Xendros (GoS) (Named)", "Devil Dog (OoW) (Named)", "Droki (OotA) (Named)", "Drow (MM)", "Drow Acolyte (OotA)", "Drow Bandit (OotA)", "Drow Cultist (OotA)", "Drow Guard (OotA)", "Drow Gunslinger (WDH)", "Drow Noble (OotA)", "Drow Scout (OotA)", "Drow Spy (OotA)", "Fel'rekt Lafeen (WDH) (Named)", "Hanne Hallen (OotA) (Named)", "Ishel (EGW) (Named)", "Junior Drow Priestess of Lolth (WDMM)", "K'thriss Drow'b (AI) (Named)", "Krebbyg Masq'il'yr (WDH) (Named)", "Nezznar the Black Spider (LMoP) (Named)", "Ollin (JttRC) (Named)", "Prolix Yusaf (CRCotN) (Named)", "Rosie Beestinger (AI) (Named)", "Sarith Kzekarit (OotA) (Named)", "Soluun Xibrindas (WDH) (Named)"], "Darkvision": ["Rosie Beestinger (AI) (Named)"], "Detect Evil and Good": ["Couatl (MM)"], "Detect Magic": ["Couatl (MM)", "Foghomer (CRCotN) (Named)", "Grandolpha Muzgardt (IDRotF) (Named)", "Xvart Warlock of Raxivort (VGM)"], "Detect Thoughts": ["Auspicia Dran (AI) (Named)", "Couatl (MM)", "Precognitive Mage (GGR)", "Thought Spy (GGR)"], "Disguise Self": ["Booyahg Slave of the Archfey (VGM)", "Deep Gnome (Svirfneblin) (MM)", "Duergar Darkhaft (OotA)", "Foghomer (CRCotN) (Named)", "Jimjar (OotA) (Named)", "K'thriss Drow'b (AI) (Named)", "Mev Flintknapper (OotA) (Named)", "Peebles (OotA) (Named)", "Reaper of Bhaal (BGDIA)", "Svirfneblin Wererat (OotA)", "The Pudding King (OotA) (Named)", "Thought Spy (GGR)", "Warlock of the Archfey (VGM)"], "Dispel Magic": ["Counterflux Blastseeker (GGR)"], "Dissonant Whispers": ["Inspired (ERLW)"], "Dream": ["Couatl (MM)"], "Druidcraft": ["Grandolpha Muzgardt (IDRotF) (Named)"], "Eldritch Blast": ["Bol'bara (EGW) (Named)", "Sahuagin Warlock of Uk'otoa (EGW)"], "Encode Thoughts|GGR": ["Thought Spy (GGR)"], "Enlarge/Reduce": ["Counterflux Blastseeker (GGR)", "Grandolpha Muzgardt (IDRotF) (Named)", "Quaggoth Thonot (MM)"], "Faerie Fire": ["Asha Vandree (OotA) (Named)", "Drow (MM)", "Drow Acolyte (OotA)", "Drow Bandit (OotA)", "Drow Cultist (OotA)", "Drow Guard (OotA)", "Drow Gunslinger (WDH)", "Drow Noble (OotA)", "Drow Scout (OotA)", "Drow Spy (OotA)", "Fel'rekt Lafeen (WDH) (Named)", "Grandolpha Muzgardt (IDRotF) (Named)", "Hanne Hallen (OotA) (Named)", "Ishel (EGW) (Named)", "Junior Drow Priestess of Lolth (WDMM)", "K'thriss Drow'b (AI) (Named)", "Krebbyg Masq'il'yr (WDH) (Named)", "Nezznar the Black Spider (LMoP) (Named)", "Sarith Kzekarit (OotA) (Named)", "Soluun Xibrindas (WDH) (Named)"], "False Life": ["Bol'bara (EGW) (Named)"], "Fear": ["Droki (OotA) (Named)"], "Feather Fall": ["Githzerai Monk (MM)", "Quaggoth Thonot (MM)"], "Fire Bolt": ["Spellix Romwod (IDRotF) (Named)", "Tarkanan Assassin (ERLW)"], "Fireball": ["Cosmotronic Blastseeker (GGR)"], "Fog Cloud": ["Kysh (GoS) (Named)", "Triton Shorestalker (MOT)"], "Friends": ["Duergar Darkhaft (OotA)", "Duergar Keeper of the Flame (OotA)"], "Gaseous Form": ["Thought Spy (GGR)"], "Greater Restoration": ["Couatl (MM)"], "Guidance": ["Oracle (MOT)"], "Guiding Bolt": ["Oracle (MOT)"], "Gust of Wind": ["Triton Shorestalker (MOT)"], "Healing Word": ["Oracle (MOT)"], "Heat Metal": ["Quaggoth Thonot (MM)"], "Hellish Rebuke": ["Captain Xendros (GoS) (Named)", "Devil Dog (OoW) (Named)", "Ollin (JttRC) (Named)", "Prolix Yusaf (CRCotN) (Named)"], "Hex": ["Bol'bara (EGW) (Named)", "Inspired (ERLW)"], "Hold Person": ["Bol'bara (EGW) (Named)", "Inspired (ERLW)", "Oracle (MOT)"], "Hunger of Hadar": ["Sahuagin Warlock of Uk'otoa (EGW)"], "Hunter's Mark": ["Albino Dwarf Spirit Warrior (ToA)", "Duergar Soulblade (MTF)", "Musharib (ToA) (Named)"], "Invisibility": ["Bol'bara (EGW) (Named)", "Grandolpha Muzgardt (IDRotF) (Named)", "Sahuagin Warlock of Uk'otoa (EGW)"], "Jump": ["Albino Dwarf Spirit Warrior (ToA)", "Duergar Soulblade (MTF)", "Githyanki Warrior (MM)", "Githzerai Monk (MM)", "Musharib (ToA) (Named)"], "Lesser Restoration": ["Couatl (MM)"], "Levitate": ["Drow Gunslinger (WDH)", "Fel'rekt Lafeen (WDH) (Named)", "Krebbyg Masq'il'yr (WDH) (Named)", "Soluun Xibrindas (WDH) (Named)"], "Light": ["Oracle (MOT)"], "Lightning Bolt": ["Anchorite of Talos (DIP)"], "Locate Object": ["Precognitive Mage (GGR)"], "Mage Armor": ["Bol'bara (EGW) (Named)", "Booyahg Slave of the Archfey (VGM)", "Counterflux Blastseeker (GGR)", "Firenewt Warlock of Imix (VGM)", "Firenewt Warlock of Imix (VGM)", "Inspired (ERLW)", "Precognitive Mage (GGR)", "Warlock of the Archfey (VGM)", "Xvart Warlock of Raxivort (VGM)"], "Mage Hand": ["Bol'bara (EGW) (Named)", "Duergar Darkhaft (OotA)", "Githyanki Warrior (MM)", "Githzerai Monk (MM)", "Inspired (ERLW)", "M\u00f4rg\u00e6n (AI) (Named)", "Nilbog (VGM)", "Quaggoth Thonot (MM)", "Spellix Romwod (IDRotF) (Named)"], "Mending": ["Grandolpha Muzgardt (IDRotF) (Named)"], "Message": ["Duergar Keeper of the Flame (OotA)"], "Minor Illusion": ["Droki (OotA) (Named)", "Rosie Beestinger (AI) (Named)", "Sahuagin Warlock of Uk'otoa (EGW)"], "Mirror Image": ["Quaggoth Thonot (MM)"], "Misty Step": ["Githyanki Warrior (MM)"], "Nondetection": ["Deep Gnome (Svirfneblin) (MM)", "Githyanki Warrior (MM)", "Jimjar (OotA) (Named)", "Mev Flintknapper (OotA) (Named)", "Peebles (OotA) (Named)", "Svirfneblin Wererat (OotA)", "The Pudding King (OotA) (Named)"], "Pass Without Trace": ["Albino Dwarf Spirit Warrior (ToA)", "Musharib (ToA) (Named)", "Rosie Beestinger (AI) (Named)"], "Poison Spray": ["Grandolpha Muzgardt (IDRotF) (Named)", "Kraul Death Priest (GGR)", "Salida (ToA) (Named)", "Yuan-ti Pureblood (MM)"], "Polymorph": ["Grandolpha Muzgardt (IDRotF) (Named)"], "Produce Flame": ["Embric (WDH) (Named)"], "Protection From Energy": ["Counterflux Blastseeker (GGR)"], "Protection From Poison": ["Couatl (MM)"], "Ray of Enfeeblement": ["Kraul Death Priest (GGR)"], "Ray of Sickness": ["Kraul Death Priest (GGR)"], "Revivify": ["Anchorite of Talos (DIP)"], "Sacred Flame": ["Rosie Beestinger (AI) (Named)"], "Sanctuary": ["Couatl (MM)", "Reaper of Bhaal (BGDIA)"], "Scorching Ray": ["Cosmotronic Blastseeker (GGR)", "Counterflux Blastseeker (GGR)"], "Scrying": ["Couatl (MM)", "Oracle (MOT)"], "See Invisibility": ["Githzerai Monk (MM)"], "Shape Water|xge": ["Shoalar Quanderil (PotA) (Named)"], "Shatter": ["Droki (OotA) (Named)"], "Shield": ["Cosmotronic Blastseeker (GGR)", "Couatl (MM)", "Githzerai Monk (MM)", "Spellix Romwod (IDRotF) (Named)"], "Shocking Grasp": ["Spellix Romwod (IDRotF) (Named)"], "Silence": ["Rosie Beestinger (AI) (Named)"], "Silent Image": ["Booyahg Slave of the Archfey (VGM)", "Spellix Romwod (IDRotF) (Named)", "Warlock of the Archfey (VGM)"], "Sleep": ["Duergar Darkhaft (OotA)"], "Speak With Animals": ["Albino Dwarf Spirit Warrior (ToA)", "Booyahg Slave of the Archfey (VGM)", "Musharib (ToA) (Named)", "Warlock of the Archfey (VGM)"], "Speak With Plants": ["Albino Dwarf Spirit Warrior (ToA)", "Musharib (ToA) (Named)"], "Stoneskin": ["Grandolpha Muzgardt (IDRotF) (Named)"], "Suggestion": ["Salida (ToA) (Named)", "Yuan-ti Pureblood (MM)"], "Tasha's Hideous Laughter": ["Nilbog (VGM)"], "Thaumaturgy": ["Captain Xendros (GoS) (Named)", "Devil Dog (OoW) (Named)", "Jandar Chergoba (WDH) (Named)", "Laiba \"Nana\" Rosse (WDH) (Named)", "Ollin (JttRC) (Named)", "Oracle (MOT)", "Prolix Yusaf (CRCotN) (Named)", "Rosie Beestinger (AI) (Named)", "Tissina Khyret (WDH) (Named)"], "Thunderwave": ["Anchorite of Talos (DIP)", "Cosmotronic Blastseeker (GGR)"], "True Strike": ["Duergar Soulblade (MTF)"], "Vampiric Touch": ["Kraul Death Priest (GGR)"], "Vicious Mockery": ["Inspired (ERLW)", "Nilbog (VGM)"]}